emlp/__init__.py
emlp/datasets.py
emlp/groups.py
emlp/utils.py
emlp/nn/__init__.py
emlp/nn/flax.py
emlp/nn/haiku.py
emlp/nn/objax.py
emlp/nn/pytorch.py
emlp/reps/__init__.py
emlp/reps/linear_operator_base.py
emlp/reps/linear_operators.py
emlp/reps/product_sum_reps.py
emlp/reps/representation.py
emlp-1.0.2.dist-info/LICENSE
emlp-1.0.2.dist-info/METADATA
emlp-1.0.2.dist-info/WHEEL
emlp-1.0.2.dist-info/top_level.txt
emlp-1.0.2.dist-info/RECORD
