Metadata-Version: 2.1
Name: emlp
Version: 1.0.2
Summary: A Practical Method for Constructing Equivariant Multilayer Perceptrons for Arbitrary Matrix Groups
Home-page: https://github.com/mfinzi/equivariant-MLP
Author: Marc Finzi
Author-email: maf820@nyu.edu
License: MIT
Keywords: equivariance,MLP,symmetry,group,AI,neural network,representation,group theory,deep learning,machine learning,rotation,Lorentz invariance
Platform: UNKNOWN
Classifier: Development Status :: 4 - Beta
Classifier: Intended Audience :: Developers
Classifier: Intended Audience :: Science/Research
Classifier: Programming Language :: Python :: 3
Classifier: Topic :: Scientific/Engineering :: Artificial Intelligence
Requires-Python: >=3.6
Requires-Dist: h5py
Requires-Dist: objax
Requires-Dist: pytest
Requires-Dist: plum-dispatch
Requires-Dist: optax
Requires-Dist: tqdm (>=4.38)
Requires-Dist: sklearn
Requires-Dist: matplotlib
Provides-Extra: expts
Requires-Dist: olive-oil-ml ; extra == 'expts'
